{
  "project_info": {
    "project_number": "345699600155",
    "project_id": "flutter-auth-a98d8",
    "storage_bucket": "flutter-auth-a98d8.firebasestorage.app"
  },
  "client": [
    {
      "client_info": {
        "mobilesdk_app_id": "1:345699600155:android:81ed4cfe475f9fa3e075be",
        "android_client_info": {
          "package_name": "com.example.myapp"
        }
      },
      "oauth_client": [],
      "api_key": [
        {
          "current_key": "AIzaSyD_gCOPVeCj5Iv5MLaDEmWWNvx0om7Q3xA"
        }
      ],
      "services": {
        "appinvite_service": {
          "other_platform_oauth_client": []
        }
      }
    }
  ],
  "configuration_version": "1"
}